django_log_formatter_asim/__init__.py
django_log_formatter_asim-1.0.0.dist-info/LICENSE
django_log_formatter_asim-1.0.0.dist-info/METADATA
django_log_formatter_asim-1.0.0.dist-info/WHEEL
django_log_formatter_asim-1.0.0.dist-info/RECORD
