Metadata-Version: 2.3
Name: django-log-formatter-asim
Version: 1.0.0
Summary: Formats Django logs in ASIM format.
License: MIT
Author: Department for Business and Trade Platform Team
Author-email: sre-team@digital.trade.gov.uk
Requires-Python: >=3.9,<4
Classifier: License :: OSI Approved :: MIT License
Classifier: Programming Language :: Python :: 3
Classifier: Programming Language :: Python :: 3.9
Classifier: Programming Language :: Python :: 3.10
Classifier: Programming Language :: Python :: 3.11
Classifier: Programming Language :: Python :: 3.12
Classifier: Programming Language :: Python :: 3.13
Requires-Dist: ddtrace (>=3.2.1,<4.0.0)
Requires-Dist: django (>=3,<5) ; python_version == "3.9"
Requires-Dist: django (>=3,<6) ; python_version >= "3.10" and python_version < "4"
Requires-Dist: pre-commit (>=3.5.0,<4.0.0)
